pushcart_deploy/__init__.py
pushcart_deploy/configuration.py
pushcart_deploy/databricks_api/__init__.py
pushcart_deploy/databricks_api/jobs_wrapper.py
pushcart_deploy/databricks_api/pipelines_wrapper.py
pushcart_deploy/databricks_api/repos_wrapper.py
pushcart_deploy/databricks_api/scheduler.py
pushcart_deploy/databricks_api/secrets_wrapper.py
pushcart_deploy/databricks_api/settings/__init__.py
pushcart_deploy/databricks_api/settings/base_settings.py
pushcart_deploy/databricks_api/settings/job_settings.py
pushcart_deploy/databricks_api/settings/pipeline_settings.py
pushcart_deploy/metadata.py
pushcart_deploy/setup.py
pushcart_deploy/validation.py
pushcart_deploy-1.6.5.dist-info/LICENSE
pushcart_deploy-1.6.5.dist-info/METADATA
pushcart_deploy-1.6.5.dist-info/WHEEL
pushcart_deploy-1.6.5.dist-info/entry_points.txt
pushcart_deploy-1.6.5.dist-info/RECORD
